dstatic/__init__.py
dstatic/dstatic.py
digital_static-0.6.0.dist-info/LICENSE
digital_static-0.6.0.dist-info/METADATA
digital_static-0.6.0.dist-info/WHEEL
digital_static-0.6.0.dist-info/entry_points.txt
digital_static-0.6.0.dist-info/top_level.txt
digital_static-0.6.0.dist-info/RECORD
