Metadata-Version: 2.1
Name: digital_static
Version: 0.6.0
Summary: static/snow simulation using python 3 and curses
Home-page: https://github.com/tech-chad/digitalstatic
Author: Chad Larson
Author-email: techchad2@gmail.com
License: MIT
Classifier: Programming Language :: Python :: 3
Classifier: Programming Language :: Python :: 3 :: Only
Classifier: Programming Language :: Python :: 3.7
Classifier: Programming Language :: Python :: 3.8
Classifier: Programming Language :: Python :: 3.9
Classifier: Programming Language :: Python :: 3.10
Requires-Python: >=3.7
License-File: LICENSE
Requires-Dist: importlib-metadata >=1.6 ; python_version < "3.8"
Requires-Dist: windows-curses ; sys_platform == "win32"
